{"dependencies":[{"name":"../../Observable","loc":{"line":3,"column":27}},{"name":"../../operator/publishLast","loc":{"line":4,"column":28}}],"generated":{"js":"\"use strict\";\nObject.defineProperty(exports, \"__esModule\", { value: true });\nvar Observable_1 = require(\"../../Observable\");\nvar publishLast_1 = require(\"../../operator/publishLast\");\nObservable_1.Observable.prototype.publishLast = publishLast_1.publishLast;\n//# sourceMappingURL=publishLast.js.map"},"hash":"a55948c2799deff1db1b365cdf56796f"}